kolibri_google_analytics_plugin/__init__.py
kolibri_google_analytics_plugin/kolibri_plugin.py
kolibri_google_analytics_plugin/options.py
kolibri_google_analytics_plugin/templates/google_analytics/head_snippet.html
kolibri_google_analytics_plugin-0.1.2.dist-info/LICENSE
kolibri_google_analytics_plugin-0.1.2.dist-info/METADATA
kolibri_google_analytics_plugin-0.1.2.dist-info/WHEEL
kolibri_google_analytics_plugin-0.1.2.dist-info/entry_points.txt
kolibri_google_analytics_plugin-0.1.2.dist-info/top_level.txt
kolibri_google_analytics_plugin-0.1.2.dist-info/RECORD
